{"id":"id7ETzoB9W","name":"McDonald's","domain":"mcdonalds.com","claimed":false,"description":"American fast food company.","longDescription":"McDonald's is a renowned brand that is passionate about providing delicious food options while consistently improving their quality. From their iconic Happy Meal® to their freshly cooked Quarter Pounder® burgers made with 100% fresh beef, McDonald's focuses on customer satisfaction and commitment to food excellence. They are dedicated to enhancing their menu and offering more balanced choices, prioritizing the use of high-quality ingredients. McDonald's nutrition calculator enables customers to access detailed nutritional information for their favorite meals, ensuring informed choices. With a team of chefs, dieticians, and suppliers, McDonald's food experts are deeply committed to ensuring the utmost quality and taste. McDonald's also offers a variety of options to cater to diverse preferences, ensuring everyone can find something they love. As a brand, McDonald's constantly evolves to provide what matters most to their valued customers.","links":[{"name":"youtube","url":"https://youtube.com/UCRI5ZedBs0_BYY4PlxD6m7w"},{"name":"twitter","url":"https://twitter.com/mcdonalds"},{"name":"instagram","url":"https://instagram.com/mcdonalds"},{"name":"facebook","url":"https://facebook.com/McDonalds"}],"logos":[{"theme":"dark","formats":[{"src":"https://asset.brandfetch.io/id7ETzoB9W/idVaG1qR03.png","background":"transparent","format":"png","height":203,"width":1619,"size":19855}],"tags":[],"type":"logo"},{"theme":"dark","formats":[{"src":"https://asset.brandfetch.io/id7ETzoB9W/idebA3SyUk.png","background":"transparent","format":"png","height":400,"width":400,"size":4697}],"tags":[],"type":"icon"},{"theme":"dark","formats":[{"src":"https://asset.brandfetch.io/id7ETzoB9W/idu6N-uDtX.svg","background":"transparent","format":"svg","size":986},{"src":"https://asset.brandfetch.io/id7ETzoB9W/idxBbqh2zu.png","background":"transparent","format":"png","height":629,"width":800,"size":31866}],"tags":[],"type":"symbol"}],"colors":[{"hex":"#ffbc0d","type":"accent","brightness":190},{"hex":"#db0007","type":"dark","brightness":47},{"hex":"#ffffff","type":"light","brightness":255}],"fonts":[{"name":"Speedee Bold","type":"title","origin":"custom","originId":null,"weights":[]},{"name":"Speedee","type":"body","origin":"custom","originId":null,"weights":[]}],"images":[{"formats":[{"src":"https://asset.brandfetch.io/id7ETzoB9W/ids1Ff0jAX.jpeg","background":null,"format":"jpeg","height":500,"width":1500,"size":30611}],"tags":[],"type":"banner"}],"qualityScore":0.91980547995137,"company":{"employees":10001,"foundedYear":1955,"industries":[{"score":0.5572443604469299,"id":"57","name":"Food and Drink","emoji":"🍔","parent":null,"slug":"food-and-drink"},{"score":0.3543822765350342,"id":"62","name":"Restaurants and Delivery","emoji":"🍔","parent":{"emoji":"🍔","id":"57","name":"Food and Drink","slug":"food-and-drink"},"slug":"restaurants-and-delivery"},{"score":0.25495263934135437,"id":"60","name":"Food and Drink","emoji":"🍔","parent":{"emoji":"🍔","id":"57","name":"Food and Drink","slug":"food-and-drink"},"slug":"food-and-drink"},{"score":0.18613506853580475,"id":"193","name":"Travel and Tourism","emoji":"✈️","parent":null,"slug":"travel-and-tourism"},{"score":0.1448691338300705,"id":"28","name":"Computers Electronics and Technology","emoji":"🖥","parent":null,"slug":"computers-electronics-and-technology"}],"kind":"PUBLIC_COMPANY","location":{"city":null,"country":null,"countryCode":null,"region":null,"state":null,"subregion":null}},"isNsfw":false}